testy_quick/__init__.py
testy_quick/check_metadata.py
testy_quick/end_functions.py
testy_quick/intermediary_functions.py
testy_quick/low_level.py
testy_quick/strings.py
testy_quick/tools_for_tests.py
testy_quick/user_string.py
testy_quick/variable_handlers/__init__.py
testy_quick/variable_handlers/base_handler.py
testy_quick/variable_handlers/conditions.py
testy_quick/variable_handlers/dataframe_handler.py
testy_quick/variable_handlers/exception_handler.py
testy_quick/variable_handlers/json_handler.py
testy_quick/variable_handlers/register.py
testy_quick/variable_handlers/to_expose.py
testy_quick-0.1.3.dist-info/LICENSE
testy_quick-0.1.3.dist-info/METADATA
testy_quick-0.1.3.dist-info/WHEEL
testy_quick-0.1.3.dist-info/top_level.txt
testy_quick-0.1.3.dist-info/RECORD
