Metadata-Version: 2.1
Name: testy-quick
Version: 0.1.3
Summary: For quickly setting up unit tests
Author: Artur Baboi
Author-email: abc05artur@gmail.com
License: Creative Commons Attribution-NonCommercial-ShareAlike 4.0 International
Keywords: python,test
Platform: UNKNOWN
Classifier: Programming Language :: Python :: 3
Classifier: Operating System :: OS Independent
Classifier: License :: Free for non-commercial use
Classifier: Development Status :: 1 - Planning
License-File: LICENSE
Requires-Dist: pandas (>=1.0)
